{
  "date": "2026-04-18",
  "totals": {
    "ProvedHere": 2699,
    "ProvedElsewhere": 497,
    "Conjectured": 325,
    "Heuristic": 27,
    "Conditional": 15,
    "Open": 3,
    "total_claims": 3566
  },
  "raw_grep_counts": {
    "_note": "Raw string occurrences (includes inline mentions in remarks/proofs). Higher than structured count.",
    "ProvedHere": 2925,
    "ProvedElsewhere": 570,
    "Conjectured": 393,
    "Heuristic": 39,
    "Conditional": 24,
    "Open": 9,
    "total_occurrences": 3960
  },
  "lines": {
    "total": 354254,
    "frame": 17868,
    "theory": 179409,
    "examples": 80828,
    "connections": 54203,
    "appendices": 21946
  },
  "by_part": {
    "connections": {
      "ProvedElsewhere": 56,
      "ProvedHere": 334,
      "Conjectured": 101,
      "Heuristic": 16,
      "Conditional": 7,
      "Open": 3
    },
    "examples": {
      "ProvedHere": 715,
      "ProvedElsewhere": 124,
      "Conjectured": 87,
      "Conditional": 3,
      "Heuristic": 2
    },
    "frame": {
      "ProvedElsewhere": 7,
      "ProvedHere": 32
    },
    "theory": {
      "ProvedElsewhere": 270,
      "ProvedHere": 1402,
      "Conjectured": 120,
      "Conditional": 5,
      "Heuristic": 9
    },
    "appendices": {
      "ProvedHere": 216,
      "ProvedElsewhere": 40,
      "Conjectured": 17
    }
  },
  "by_file": {
    "appendices/_sl2_yangian_insert.tex": {
      "ProvedHere": 8
    },
    "appendices/arnold_relations.tex": {
      "ProvedElsewhere": 3,
      "ProvedHere": 6
    },
    "appendices/branch_line_reductions.tex": {
      "ProvedHere": 21,
      "Conjectured": 1
    },
    "appendices/combinatorial_frontier.tex": {
      "Conjectured": 2,
      "ProvedHere": 1
    },
    "appendices/dual_methodology.tex": {
      "ProvedElsewhere": 4,
      "ProvedHere": 1
    },
    "appendices/hochschild_conventions.tex": {
      "ProvedHere": 1
    },
    "appendices/homotopy_transfer.tex": {
      "ProvedHere": 6,
      "ProvedElsewhere": 9
    },
    "appendices/koszul_reference.tex": {
      "ProvedElsewhere": 5,
      "ProvedHere": 7
    },
    "appendices/nonlinear_modular_shadows.tex": {
      "ProvedHere": 69,
      "ProvedElsewhere": 1,
      "Conjectured": 9
    },
    "appendices/ordered_associative_chiral_kd.tex": {
      "ProvedHere": 89,
      "Conjectured": 4,
      "ProvedElsewhere": 5
    },
    "appendices/q_convention_bridge_appendix.tex": {
      "ProvedHere": 2
    },
    "appendices/signs_and_shifts.tex": {
      "ProvedHere": 4,
      "ProvedElsewhere": 11
    },
    "appendices/spectral_higher_genus.tex": {
      "ProvedHere": 1,
      "ProvedElsewhere": 2,
      "Conjectured": 1
    },
    "chapters/connections/arithmetic_shadows.tex": {
      "ProvedElsewhere": 13,
      "ProvedHere": 122,
      "Conjectured": 17,
      "Heuristic": 2,
      "Conditional": 1
    },
    "chapters/connections/bv_brst.tex": {
      "ProvedElsewhere": 7,
      "Heuristic": 5,
      "ProvedHere": 14,
      "Conjectured": 3,
      "Conditional": 4
    },
    "chapters/connections/concordance.tex": {
      "ProvedHere": 15,
      "ProvedElsewhere": 8,
      "Conjectured": 11,
      "Heuristic": 1,
      "Open": 3
    },
    "chapters/connections/editorial_constitution.tex": {
      "ProvedElsewhere": 3,
      "Conjectured": 11,
      "Conditional": 1,
      "ProvedHere": 7
    },
    "chapters/connections/entanglement_modular_koszul.tex": {
      "ProvedElsewhere": 2,
      "ProvedHere": 6,
      "Conjectured": 4,
      "Heuristic": 2
    },
    "chapters/connections/feynman_connection.tex": {
      "ProvedElsewhere": 1,
      "Conjectured": 2
    },
    "chapters/connections/feynman_diagrams.tex": {
      "Heuristic": 1,
      "Conjectured": 5,
      "ProvedHere": 11,
      "ProvedElsewhere": 2
    },
    "chapters/connections/frontier_modular_holography_platonic.tex": {
      "ProvedHere": 53,
      "Conjectured": 14,
      "ProvedElsewhere": 3,
      "Heuristic": 2
    },
    "chapters/connections/genus1_seven_faces.tex": {
      "ProvedHere": 10,
      "Conjectured": 1
    },
    "chapters/connections/genus_complete.tex": {
      "ProvedElsewhere": 6,
      "ProvedHere": 28,
      "Conjectured": 8,
      "Heuristic": 1
    },
    "chapters/connections/holographic_codes_koszul.tex": {
      "ProvedHere": 6,
      "Conjectured": 2
    },
    "chapters/connections/holographic_datum_master.tex": {
      "ProvedElsewhere": 2,
      "ProvedHere": 10,
      "Heuristic": 2
    },
    "chapters/connections/master_concordance.tex": {
      "ProvedHere": 1
    },
    "chapters/connections/outlook.tex": {
      "ProvedElsewhere": 1,
      "Conjectured": 2
    },
    "chapters/connections/poincare_computations.tex": {
      "Conjectured": 1,
      "ProvedHere": 2
    },
    "chapters/connections/semistrict_modular_higher_spin_w3.tex": {
      "ProvedHere": 16,
      "Conjectured": 4
    },
    "chapters/connections/subregular_hook_frontier.tex": {
      "ProvedHere": 17,
      "Conditional": 1,
      "Conjectured": 4
    },
    "chapters/connections/thqg_entanglement_programme.tex": {
      "ProvedHere": 5,
      "Conjectured": 11
    },
    "chapters/connections/thqg_introduction_supplement_body.tex": {
      "ProvedElsewhere": 8
    },
    "chapters/connections/thqg_open_closed_realization.tex": {
      "ProvedHere": 11,
      "Conjectured": 1
    },
    "chapters/examples/bar_complex_tables.tex": {
      "ProvedHere": 26
    },
    "chapters/examples/bershadsky_polyakov.tex": {
      "ProvedElsewhere": 1,
      "ProvedHere": 8
    },
    "chapters/examples/beta_gamma.tex": {
      "ProvedElsewhere": 6,
      "ProvedHere": 27,
      "Conjectured": 2
    },
    "chapters/examples/chiral_moonshine_unified.tex": {
      "ProvedHere": 5,
      "ProvedElsewhere": 4
    },
    "chapters/examples/deformation_quantization.tex": {
      "ProvedElsewhere": 11,
      "ProvedHere": 7,
      "Conjectured": 2
    },
    "chapters/examples/deformation_quantization_examples.tex": {
      "ProvedElsewhere": 6,
      "ProvedHere": 2
    },
    "chapters/examples/exceptional_yangian_koszul_duality_platonic.tex": {
      "ProvedElsewhere": 2,
      "ProvedHere": 9
    },
    "chapters/examples/free_fields.tex": {
      "ProvedHere": 66,
      "ProvedElsewhere": 15,
      "Conjectured": 8,
      "Conditional": 1
    },
    "chapters/examples/genus_expansions.tex": {
      "ProvedHere": 40,
      "Conjectured": 4,
      "ProvedElsewhere": 4
    },
    "chapters/examples/heisenberg_eisenstein.tex": {
      "ProvedHere": 18,
      "ProvedElsewhere": 4
    },
    "chapters/examples/kac_moody.tex": {
      "ProvedHere": 55,
      "ProvedElsewhere": 14,
      "Conjectured": 12
    },
    "chapters/examples/landscape_census.tex": {
      "ProvedHere": 23,
      "Conjectured": 7,
      "ProvedElsewhere": 1
    },
    "chapters/examples/lattice_foundations.tex": {
      "ProvedHere": 45,
      "ProvedElsewhere": 3,
      "Conjectured": 3
    },
    "chapters/examples/level1_bridge.tex": {
      "ProvedHere": 3
    },
    "chapters/examples/logarithmic_w_algebras.tex": {
      "ProvedHere": 2,
      "ProvedElsewhere": 2,
      "Conjectured": 4
    },
    "chapters/examples/minimal_model_examples.tex": {
      "ProvedElsewhere": 3,
      "ProvedHere": 5
    },
    "chapters/examples/minimal_model_fusion.tex": {
      "ProvedElsewhere": 8,
      "ProvedHere": 12
    },
    "chapters/examples/moonshine.tex": {
      "ProvedHere": 1
    },
    "chapters/examples/n2_superconformal.tex": {
      "ProvedHere": 3,
      "Conjectured": 1
    },
    "chapters/examples/shadow_tower_extended_families.tex": {
      "ProvedElsewhere": 2,
      "ProvedHere": 8,
      "Conjectured": 3
    },
    "chapters/examples/symmetric_orbifolds.tex": {
      "ProvedHere": 6,
      "Conjectured": 3
    },
    "chapters/examples/w3_composite_fields.tex": {
      "ProvedHere": 13,
      "ProvedElsewhere": 2
    },
    "chapters/examples/w3_holographic_datum.tex": {
      "ProvedElsewhere": 4,
      "ProvedHere": 7
    },
    "chapters/examples/w_algebras.tex": {
      "ProvedHere": 70,
      "Conjectured": 7,
      "ProvedElsewhere": 18,
      "Heuristic": 2
    },
    "chapters/examples/w_algebras_deep.tex": {
      "ProvedElsewhere": 6,
      "ProvedHere": 37,
      "Conjectured": 3
    },
    "chapters/examples/y_algebras.tex": {
      "ProvedHere": 14
    },
    "chapters/examples/yangians_computations.tex": {
      "ProvedElsewhere": 4,
      "Conjectured": 9,
      "ProvedHere": 59,
      "Conditional": 2
    },
    "chapters/examples/yangians_drinfeld_kohno.tex": {
      "ProvedHere": 97,
      "Conjectured": 11
    },
    "chapters/examples/yangians_foundations.tex": {
      "ProvedElsewhere": 4,
      "Conjectured": 8,
      "ProvedHere": 47
    },
    "chapters/frame/guide_to_main_results.tex": {
      "ProvedElsewhere": 1,
      "ProvedHere": 1
    },
    "chapters/frame/heisenberg_frame.tex": {
      "ProvedHere": 12,
      "ProvedElsewhere": 6
    },
    "chapters/frame/part_ii_platonic_introduction.tex": {
      "ProvedHere": 6
    },
    "chapters/frame/part_iii_platonic_introduction.tex": {
      "ProvedHere": 6
    },
    "chapters/frame/part_iv_platonic_introduction.tex": {
      "ProvedHere": 6
    },
    "chapters/frame/programme_overview_platonic.tex": {
      "ProvedHere": 1
    },
    "chapters/theory/algebraic_foundations.tex": {
      "ProvedElsewhere": 14,
      "ProvedHere": 6,
      "Conjectured": 1
    },
    "chapters/theory/all_tier_generating_function_platonic.tex": {
      "ProvedHere": 9
    },
    "chapters/theory/bar_cobar_adjunction_curved.tex": {
      "ProvedHere": 113,
      "ProvedElsewhere": 34
    },
    "chapters/theory/bar_cobar_adjunction_inversion.tex": {
      "ProvedElsewhere": 5,
      "ProvedHere": 54,
      "Conjectured": 13
    },
    "chapters/theory/bar_construction.tex": {
      "ProvedHere": 25,
      "ProvedElsewhere": 2
    },
    "chapters/theory/chern_weil_level_shift_platonic.tex": {
      "ProvedHere": 5
    },
    "chapters/theory/chiral_center_theorem.tex": {
      "ProvedHere": 13,
      "ProvedElsewhere": 1
    },
    "chapters/theory/chiral_climax_platonic.tex": {
      "ProvedElsewhere": 10,
      "ProvedHere": 7,
      "Conjectured": 4
    },
    "chapters/theory/chiral_hochschild_koszul.tex": {
      "ProvedHere": 50,
      "Conjectured": 17,
      "ProvedElsewhere": 3
    },
    "chapters/theory/chiral_koszul_pairs.tex": {
      "ProvedHere": 53,
      "ProvedElsewhere": 4,
      "Conditional": 1,
      "Conjectured": 3,
      "Heuristic": 1
    },
    "chapters/theory/chiral_modules.tex": {
      "ProvedHere": 49,
      "ProvedElsewhere": 14,
      "Conjectured": 4
    },
    "chapters/theory/climax_theorem.tex": {
      "ProvedHere": 4,
      "Conjectured": 3
    },
    "chapters/theory/clutching_uniqueness_platonic.tex": {
      "ProvedHere": 4,
      "Conditional": 1
    },
    "chapters/theory/cobar_construction.tex": {
      "ProvedElsewhere": 9,
      "ProvedHere": 29,
      "Conjectured": 4
    },
    "chapters/theory/coderived_models.tex": {
      "ProvedElsewhere": 2,
      "ProvedHere": 7
    },
    "chapters/theory/compact_completed_mc3_comparison_platonic.tex": {
      "ProvedHere": 5,
      "ProvedElsewhere": 1
    },
    "chapters/theory/computational_methods.tex": {
      "ProvedHere": 17,
      "ProvedElsewhere": 1
    },
    "chapters/theory/configuration_spaces.tex": {
      "ProvedElsewhere": 31,
      "ProvedHere": 37,
      "Heuristic": 1,
      "Conjectured": 1
    },
    "chapters/theory/conformal_anomaly_rigidity_platonic.tex": {
      "ProvedHere": 6,
      "ProvedElsewhere": 1
    },
    "chapters/theory/derived_langlands.tex": {
      "ProvedHere": 11,
      "ProvedElsewhere": 4,
      "Heuristic": 1,
      "Conjectured": 6
    },
    "chapters/theory/e1_modular_koszul.tex": {
      "ProvedHere": 23,
      "Conjectured": 1
    },
    "chapters/theory/e3_identification_chain_level_platonic.tex": {
      "ProvedHere": 5
    },
    "chapters/theory/en_koszul_duality.tex": {
      "ProvedHere": 40,
      "ProvedElsewhere": 12,
      "Conjectured": 6
    },
    "chapters/theory/existence_criteria.tex": {
      "ProvedElsewhere": 5,
      "ProvedHere": 2
    },
    "chapters/theory/filtered_curved.tex": {
      "ProvedHere": 2
    },
    "chapters/theory/fourier_seed.tex": {
      "ProvedHere": 14,
      "ProvedElsewhere": 2
    },
    "chapters/theory/ftm_seven_fold_tfae_platonic.tex": {
      "ProvedHere": 12
    },
    "chapters/theory/genus_2_ddybe_platonic.tex": {
      "ProvedElsewhere": 2,
      "ProvedHere": 2,
      "Conjectured": 1
    },
    "chapters/theory/higher_genus_complementarity.tex": {
      "ProvedHere": 81,
      "Conditional": 1,
      "Conjectured": 3,
      "Heuristic": 2
    },
    "chapters/theory/higher_genus_foundations.tex": {
      "ProvedHere": 67,
      "ProvedElsewhere": 23,
      "Conditional": 1
    },
    "chapters/theory/higher_genus_modular_koszul.tex": {
      "ProvedHere": 269,
      "Conjectured": 20,
      "ProvedElsewhere": 11,
      "Heuristic": 2
    },
    "chapters/theory/higher_kummer_arithmetic_duality_platonic.tex": {
      "ProvedHere": 3
    },
    "chapters/theory/hochschild_cohomology.tex": {
      "ProvedElsewhere": 16,
      "ProvedHere": 12
    },
    "chapters/theory/infinite_fingerprint_classification.tex": {
      "ProvedHere": 8
    },
    "chapters/theory/introduction.tex": {
      "Conjectured": 1,
      "ProvedElsewhere": 1,
      "ProvedHere": 2
    },
    "chapters/theory/kappa_conductor.tex": {
      "ProvedHere": 2,
      "Conjectured": 3
    },
    "chapters/theory/koszul_pair_structure.tex": {
      "ProvedHere": 29,
      "ProvedElsewhere": 11,
      "Heuristic": 1,
      "Conjectured": 13
    },
    "chapters/theory/koszulness_moduli_scheme.tex": {
      "ProvedHere": 11,
      "ProvedElsewhere": 1
    },
    "chapters/theory/koszulness_vii_multiweight_platonic.tex": {
      "ProvedHere": 5,
      "ProvedElsewhere": 1
    },
    "chapters/theory/mc3_five_family_platonic.tex": {
      "ProvedHere": 8,
      "ProvedElsewhere": 2,
      "Conjectured": 1
    },
    "chapters/theory/mc5_class_m_chain_level_platonic.tex": {
      "ProvedHere": 5,
      "ProvedElsewhere": 1
    },
    "chapters/theory/mc5_genus0_genus1_wall_platonic.tex": {
      "ProvedHere": 4,
      "Conjectured": 1
    },
    "chapters/theory/motivic_shadow_full_class_m_platonic.tex": {
      "ProvedHere": 8
    },
    "chapters/theory/motivic_shadow_tower.tex": {
      "ProvedHere": 10
    },
    "chapters/theory/nilpotent_completion.tex": {
      "ProvedHere": 10,
      "ProvedElsewhere": 3
    },
    "chapters/theory/ordered_associative_chiral_kd.tex": {
      "ProvedHere": 90,
      "Conjectured": 3,
      "Heuristic": 1,
      "ProvedElsewhere": 2
    },
    "chapters/theory/periodic_cdg_admissible.tex": {
      "ProvedHere": 5,
      "Conjectured": 1
    },
    "chapters/theory/poincare_duality.tex": {
      "ProvedElsewhere": 1,
      "ProvedHere": 8
    },
    "chapters/theory/poincare_duality_quantum.tex": {
      "ProvedElsewhere": 10,
      "Conjectured": 4,
      "ProvedHere": 11
    },
    "chapters/theory/quantum_corrections.tex": {
      "ProvedHere": 3,
      "ProvedElsewhere": 3
    },
    "chapters/theory/shadow_L_function_platonic.tex": {
      "ProvedHere": 6
    },
    "chapters/theory/shadow_tower_higher_coefficients.tex": {
      "ProvedHere": 41,
      "Conjectured": 1,
      "ProvedElsewhere": 1
    },
    "chapters/theory/shadow_tower_other_class_M_platonic.tex": {
      "ProvedHere": 20,
      "Conjectured": 3
    },
    "chapters/theory/shadow_tower_quadrichotomy_platonic.tex": {
      "ProvedElsewhere": 10,
      "ProvedHere": 10,
      "Conditional": 1,
      "Conjectured": 1
    },
    "chapters/theory/shadow_tower_sub_subleading_platonic.tex": {
      "ProvedHere": 8
    },
    "chapters/theory/spectral_sequences.tex": {
      "ProvedElsewhere": 12,
      "ProvedHere": 3
    },
    "chapters/theory/theorem_A_infinity_2.tex": {
      "ProvedHere": 14,
      "ProvedElsewhere": 2
    },
    "chapters/theory/theorem_B_scope_platonic.tex": {
      "ProvedHere": 3,
      "ProvedElsewhere": 1
    },
    "chapters/theory/theorem_C_refinements_platonic.tex": {
      "ProvedHere": 1
    },
    "chapters/theory/theorem_h_off_koszul_platonic.tex": {
      "ProvedHere": 5
    },
    "chapters/theory/three_hochschild_unification_platonic.tex": {
      "ProvedHere": 4
    },
    "chapters/theory/three_invariants.tex": {
      "ProvedHere": 5
    },
    "chapters/theory/topologization_chain_level_platonic.tex": {
      "ProvedHere": 9
    },
    "chapters/theory/universal_conductor_K_platonic.tex": {
      "ProvedHere": 2,
      "Conjectured": 1
    },
    "chapters/theory/virasoro_motivic_purity.tex": {
      "ProvedElsewhere": 1,
      "ProvedHere": 5
    },
    "chapters/theory/virasoro_motivic_purity_all_r_platonic.tex": {
      "ProvedHere": 6
    },
    "chapters/theory/z_g_kummer_bernoulli_platonic.tex": {
      "ProvedHere": 5
    }
  }
}